patchwork/websoccer/__init__.py
patchwork/websoccer/fastapi.py
patchwork/websoccer/client/__init__.py
patchwork/websoccer/client/base.py
patchwork/websoccer/client/websock.py
patchwork/websoccer/court/__init__.py
patchwork/websoccer/court/base.py
patchwork/websoccer/court/local.py
patchwork/websoccer/court/patchwork.py
patchwork/websoccer/router/__init__.py
patchwork/websoccer/router/base.py
tests/__init__.py
tests/conftest.py
tests/test_usage.py
patchwork_websoccer-0.2.0.dist-info/LICENSE
patchwork_websoccer-0.2.0.dist-info/METADATA
patchwork_websoccer-0.2.0.dist-info/WHEEL
patchwork_websoccer-0.2.0.dist-info/top_level.txt
patchwork_websoccer-0.2.0.dist-info/RECORD
