Metadata-Version: 2.1
Name: patchwork-websoccer
Version: 0.2.0
Summary: Websockets integration for Patchwork - The distributed asynchronous microframework
Home-page: 
Author: Pawel Pecio
Author-email: 
Classifier: Development Status :: 5 - Production/Stable
Classifier: License :: OSI Approved :: MIT License
Classifier: Operating System :: POSIX :: Linux
Classifier: Programming Language :: Python :: 3.7
Classifier: Programming Language :: Python :: 3.8
Classifier: Programming Language :: Python :: 3.9
Classifier: Programming Language :: Python :: 3.10
Classifier: Programming Language :: Python :: Implementation :: CPython
Classifier: Topic :: Software Development :: Libraries :: Application Frameworks
License-File: LICENSE
Requires-Dist: humanize >=3.11.0
Requires-Dist: importlib-metadata >=4.8.1
Requires-Dist: patchwork-core ~=0.2
Requires-Dist: patchwork-contrib[fastapi] >=0.1.0
Requires-Dist: aioredis >=2.0.1
Requires-Dist: ujson >=5.1.0
Provides-Extra: starlette
Requires-Dist: starlette ; extra == 'starlette'
